pylibrm/RMAxis.py
pylibrm/__init__.py
pylibrm/constant.py
pylibrm-0.0.6.dist-info/LICENSE.txt
pylibrm-0.0.6.dist-info/METADATA
pylibrm-0.0.6.dist-info/WHEEL
pylibrm-0.0.6.dist-info/top_level.txt
pylibrm-0.0.6.dist-info/RECORD
