Metadata-Version: 2.1
Name: pylibrm
Version: 0.0.6
Summary: Python lib for RobustMotion axis
Home-page: UNKNOWN
Author: Alan Huang
Author-email: alanhuang@rmaxis.com
License: UNKNOWN
Platform: UNKNOWN
Classifier: Programming Language :: Python :: 3
Classifier: License :: OSI Approved :: MIT License
Classifier: Operating System :: OS Independent
Requires-Python: >=3.6
License-File: LICENSE.txt
Requires-Dist: pymodbus (==2.5.3)
